maqal/__init__.py
maqal/maqal.py
maqal/storage/uyghur-maqal-temsilliri.db
maqal/storage/uyghur-maqal-temsilliri.json
maqal/storage/uyghur-maqal-temsilliri.txt
maqal-1.0.2.dist-info/LICENSE
maqal-1.0.2.dist-info/METADATA
maqal-1.0.2.dist-info/WHEEL
maqal-1.0.2.dist-info/top_level.txt
maqal-1.0.2.dist-info/RECORD
