Metadata-Version: 2.1
Name: maqal
Version: 1.0.2
Summary: Uighur language idiom tool
Home-page: https://github.com/kompasim/uyghur-maqal-temsilliri
Author: kompasim
Author-email: kompasim@163.com
License: MIT Licence
Keywords: uyghur,uighur,maqal,makal,temsil,tamsil
Platform: any
Classifier: Programming Language :: Python :: 3
Classifier: License :: OSI Approved :: MIT License
Classifier: Operating System :: OS Independent
